pyseed/__init__.py
pyseed/apibase.py
pyseed/exceptions.py
pyseed/seed_client.py
pyseed/seed_client_base.py
pyseed/utils.py
tests/__init__.py
tests/test_apibase.py
tests/test_seed_base.py
tests/test_seed_client.py
tests/test_seed_client_base.py
tests/test_utils.py
py_SEED-0.5.1.dist-info/LICENSE
py_SEED-0.5.1.dist-info/METADATA
py_SEED-0.5.1.dist-info/WHEEL
py_SEED-0.5.1.dist-info/top_level.txt
py_SEED-0.5.1.dist-info/RECORD
